Workbook

Sheet 成飞系统件
A1: 成飞发货清单-2026.4.23产品已发
A2: 本次发货共计1# | J2: 发货日期： | K2: 46135
A3: 序号 | B3: 产品名称 | C3: 型号 | D3: 规 格 | E3: 材 料 | F3: 发货数量 | G3: 批次号 | H3: 提货单号 | I3: 箱号 | J3: 备注(订单号) | K3: 产品保管期 | L3: 产品油封期 | O3: =VLOOKUP(P3,[1]交付期日!D:X,21,FALSE) -> #N/A | P3: =VLOOKUP(H3,[1]匹配!B:AF,31,FALSE) -> 销售订单行
A4: 1 | D4: - | E4: 组件(20) | F4: 26 | G4: G2603-0106 | H4: 7101084529 | I4: 1# | J4: 司采购-26-1-A17-3265-001 | M4: 1084529 | O4: #N/A | P4: 1100160907/10

Sheet 成飞采购部
A1: 贵州航天精工制造有限公司发货清单 | P1: =VLOOKUP(M1,[2]匹配!B:AF,31,FALSE) -> #N/A | R1: =VLOOKUP(M1,[2]匹配!B:G,6,FALSE) -> #N/A
A2: 序号 | B2: 订单序号 | C2: 订单号 | D2: 物料编码 | E2: 图号 | F2: 批次号 | G2: 到货数量 | H2: 到货数量 | I2: 材料 | J2: 油封期限 | K2: 保质期 | L2: 备注 | M2: 发货通知单号 | N2: 交付期日 | P2: =VLOOKUP(M2,[2]匹配!B:AF,31,FALSE) -> #N/A | R2: =VLOOKUP(M2,[2]匹配!B:G,6,FALSE) -> #N/A
A3: 1 | B3: 1 | C3: 司采购-25-1-A13-3042-007 | D3: 10010772 | F3: G2604-0917 | G3: 46 | H3: 46 | I3: 5860 | K3: 2026.4.21-2028.4.20 | L3: 批产 | M3: 7101105556 | N3: 46183 | O3: 1105556 | P3: 1100162715/50 | R3: 28 | S3: 1# | T3: 2026.4.25已发

Sheet 北京星航
A1: 装 箱 单
A2: 收货单位：北京星航机电装备有限公司 | F2: 单据编号:20250524-001 | K2: 货物总箱数:1#
A3: 提货单号 | B3: 批号 | C3: 采用标准 | D3: 规格 | E3: 材质 | F3: 性能等级 | G3: 表面处理 | H3: 单件 | I3: 提货数量 | J3: 价格 | K3: 提货金额 | L3: 清单备注邀请 | M3: 箱号
A4: 7100945254 | B4: G2412-0355 | D4: M10 | E4: ML1Cr17Ni2 | F4: 30-36HRC | G4: ECP | H4: 件 | I4: 8 | J4: 9.6 | K4: 76.8 | L4: 2023/X-07-0112 | M4: 1# | N4: 945254
A5: 内装清单 证件资料

Sheet 182
A1: 贵州航天精工制造有限公司发货汇总清单-182 | M1: =7100&N1 -> 7100 | O1: =VLOOKUP(M1,[3]匹配!B:F,5,FALSE) -> #N/A | P1: =VLOOKUP(M1,[3]匹配!B:G,6,FALSE) -> #N/A | Q1: =VLOOKUP(M1,[3]匹配!B:AF,31,FALSE) -> #N/A
A2: 发货日期2026.4.25 使用部门：库房 | M2: =7100&N2 -> 7100 | O2: =VLOOKUP(M2,[3]匹配!B:F,5,FALSE) -> #N/A | P2: =VLOOKUP(M2,[3]匹配!B:G,6,FALSE) -> #N/A | Q2: =VLOOKUP(M2,[3]匹配!B:AF,31,FALSE) -> #N/A
A3: 序号 | B3: 标准件号 | C3: 标准名称 | D3: 交付数量 | E3: 单价 | F3: 总价 | G3: 批次号 | H3: 生产日期 | I3: 表面处理 | J3: 试验件及报告携带情况 | K3: 箱号 | L3: 合同编号 | M3: =7100&N3 -> 7100 | O3: =VLOOKUP(M3,[3]匹配!B:F,5,FALSE) -> #N/A | P3: =VLOOKUP(M3,[3]匹配!B:G,6,FALSE) -> #N/A | Q3: =VLOOKUP(M3,[3]匹配!B:AF,31,FALSE) -> #N/A
A4: 1 | D4: 41 | E4: 60 | F4: 2460 | G4: G2512-0621 | H4: 46137 | J4: 无三方试验 | K4: 1# | L4: S0234032025000820 | M4: 7101107676 | N4: 1107676 | O4: YSD601 | P4: 1A | Q4: 1100156818/10
A5: 合计 | D5: 41 | E5: 60 | F5: 2460 | M5: 7100 | O5: #N/A | P5: #N/A | Q5: #N/A

Sheet 331
A1: #N/A | B1: 装箱清单-331-2026.4.27产品已发 | N1: 710 | Q1: #N/A | R1: #N/A
A2: 销售订单行 | B2: 箱号 | C2: 发货日期 | D2: 名称 | E2: 型号 | F2: 规格 | G2: 数量 | H2: 批次号 | I2: 提货单号 | J2: 331订单号 | K2: 机型 | L2: 运单 | M2: 备注 | N2: 710 | Q2: 物料编号 | R2: 331码
A3: 1100160834/150 | B3: 1443# | C3: 46139 | F3: 10Ag | G3: 31 | H3: G2602-7531 | I3: 7101108137 | L3: SF1569263594141 | N3: 7101108137 | O3: 1108137 | Q3: 000042944319124082 | R3: #N/A

Sheet 410
A1: 发货单编号 | C1: 到货单号
A2: 供应商名称 | B2: 贵州航天精工制造有限公司 | C2: 发货地址 | D2: 浙江省温州市瑞安市塘下镇场桥上灶工业区 | E2: 物流单号／航班号
A3: 到货仓库 | C3: 收货地址 | D3: 辽宁省沈阳市浑南区仙桃二街航空动力产业园三期5号库东南门 | E3: 交付方式
A4: 发货日期 | B4: 2026.04.24 | C4: 预计到货日期 | E4: 总箱数／捆数 | F4: 1箱
A5: 发货人 | C5: 联系电话 | E5: 总件（批次）数
A6: 承运人 | B6: 顺丰郎先生 | C6: 联系电话 | E6: 总重量（含包装箱）(kg）
A7: 收货人 | B7: 张珂瑶 | C7: 联系电话
A11: 1 | B11: 箱号 | C11: 采购员 | D11: 订单编号｜行号 | E11: PART码 | F11: 图号 | G11: 物料名称 | H11: 制造型号序号 | I11: 修程 | J11: 军民品 | K11: 计量单位 | L11: 例如
B12: 1 | C12: 张珂瑶 | H12: / | I12: / | J12: 军品 | K12: 个
C13: 供应商批次 | D13: 供应商顺序号 | E13: 随机文件数量 | F13: 是否为附带备件 | G13: 理化件数量 | H13: 零件数量 | I13: 光盘数量 | J13: 物料版本 | K13: 备注
D14: / | E14: 1 | F14: 否 | G14: / | I14: 无 | J14: 无 | K14: 100％国产化
A15: 2 | B15: 箱号 | C15: 采购员 | D15: 订单编号｜行号 | E15: PART码 | F15: 图号 | G15: 物料名称 | H15: 制造型号序号 | I15: 修程 | J15: 军民品 | K15: 计量单位
B16: 1 | C16: 张珂瑶 | H16: / | I16: / | J16: 军品 | K16: 个
C17: 供应商批次 | D17: 供应商顺序号 | E17: 随机文件数量 | F17: 是否为附带备件 | G17: 理化件数量 | H17: 零件数量 | I17: 光盘数量 | J17: 物料版本 | K17: 备注
D18: / | F18: 否 | G18: / | I18: 无 | J18: 无 | K18: 100％国产化
A21: 410装箱单-2026.4.28已发
A22: 箱号 | B22: 牌号 | C22: 批次号 | D22: 数量 （件） | E22: 合计数量 | F22: 清单号 | G22: 备注1 | H22: 收货人 | I22: 合同号 | K22: 备注 | L22: 发货日期
A23: 1# | C23: G2604-0943 | D23: 24 | F23: 7101108166 | H23: 张珂瑶 | L23: 46140 | M23: 1108166 | O23: - | P23: 内六角螺钉
C24: G2604-0944 | D24: 24 | F24: 7101108217 | H24: 张珂瑶 | L24: 46140 | M24: 1108217 | O24: - | P24: 内六角螺钉(加长)

Sheet 420
A1: 420发货清单-张毕轩-2026.4.27产品已发 | Q1: =710&R1 -> 710 | S1: =VLOOKUP(Q1,[4]数据!B:AE,30,FALSE) -> #N/A | T1: =VLOOKUP(Q1,[4]数据!B:F,5,FALSE) -> #N/A | U1: =VLOOKUP(Q1,[4]数据!B:G,6,FALSE) -> #N/A
A2: 序号 | B2: 箱号 | C2: 发货时间 | D2: 零件名称 | E2: 零件号/规格 | F2: 版次 | G2: 产品状态 | H2: 批次号 | I2: 单件重量/G | J2: 订货数量 | K2: 发货数量 | L2: 合同单价 | M2: 运单号 | N2: 追溯码 | O2: 合同号/订货单号 | Q2: =710&R2 -> 710 | S2: =VLOOKUP(Q2,[4]数据!B:AE,30,FALSE) -> #N/A | T2: =VLOOKUP(Q2,[4]数据!B:F,5,FALSE) -> #N/A | U2: =VLOOKUP(Q2,[4]数据!B:G,6,FALSE) -> #N/A
A3: 1 | B3: 1# | C3: 46139 | F3: G | G3: 已完成合格认证 | H3: G2601-2607 | I3: 1.2 | J3: 50 | K3: 23 | L3: 107 | M3: SF1569263586676 | O3: DHH2026010098 | Q3: 7101108214 | R3: 1108214 | S3: G-100015358-260206-0033 | T3: MS51830(G版) | U3: CA201L

Sheet 430
A1: 430装箱单-2026.4.27产品已发 | M1: 发货之前填写订单数量，交付日期，合同号，没有问姚晗 | N1: =VLOOKUP(F1,[5]数据!B:G,6,FALSE) -> #N/A
A2: 序号 | B2: 牌号 | C2: 批次号 | D2: 数量（件） | E2: 订单数量 | F2: 清单号 | G2: 备注 | H2: 收货人 | I2: 合同号 | J2: 交付日期 | K2: 日期 | M2: =VLOOKUP(F2,[5]数据!B:F,5,FALSE) -> #N/A | N2: =VLOOKUP(F2,[5]数据!B:G,6,FALSE) -> #N/A
A3: 1# | C3: G2510-0520 | D3: 171 | E3: 订单数量:365 | F3: 7101095411 | G3: X20 | H3: 刘苗 | J3: 45991 | K3: 46139 | L3: 1095411 | M3: S10.2.1157 | O3: 订单数量:

Sheet 460
A1: 贵州航天精工发货清单--460-2026.4.27产品已发
A2: 序号 | B2: 产品名称 | C2: 客户物料码 | D2: 采用标准 | E2: 规 格 | F2: 材 料 | G2: 发货数量 | H2: 批次号 | I2: 提货单号 | J2: 订单行号 | K2: 客户订单行号 | L2: 客户特殊要求 | M2: 橡胶保质期 | N2: 箱号 | O2: 发货日期
A3: 1 | E3: - | F3: GH536 | G3: 278 | H3: G2603-1012 | I3: 7101106510 | J3: 1100156449/50 | K3: 4500024452-680 | L3: 16659421 | N3: 1546# | O3: 46139 | P3: 1106510

Sheet 凌云科技
A1: 凌云科技集团装箱单 | N1: ="710"&O1 -> 710
A2: 序号 | B2: 产品名称 | C2: 型号 | D2: 规 格 | E2: 性能等级 | F2: 表面处理 | G2: 材料 | H2: 发货数量 | I2: 批次号 | J2: 清单备注 | K2: 客户特殊要求 | L2: 箱号 | M2: 发货日期 | N2: ="710"&O2 -> 710
A3: 1 | D3: 8×160 | G3: 组件(铜) | H3: 155 | I3: G2602-0481 | L3: 1# | M3: 46137 | N3: 7101106547 | O3: 1106547

Sheet 5719
A1: 航天精工股份有限贵州公司发货清单 | Q1: #N/A | R1: #N/A | S1: #N/A
A2: 发货时间： | C2: 46126 | D2: 本次发货共2箱 | L2: 收货人：王延泽 | Q2: #N/A | R2: #N/A | S2: #N/A
A3: 箱号 | B3: 发货时间 | C3: 零件名称 | D3: 零件号/规格 | E3: 规格 | F3: 版次 | G3: 订货数量 | H3: 发货数量 | I3: 合计数量 | J3: 批次号 | K3: 合同单价 | L3: 运单 | M3: 提货单号 | N3: 合同号（若有） | Q3: 客户采购订单编号 | R3: 采用标准 | S3: 规格
A4: 1# | B4: 46126 | E4: - | G4: 1008 | H4: 898 | I4: 898 | J4: G2510-0846 | K4: 175 | L4: SF1566631842360 | M4: 7101101388 | N4: （2026）N35365719 | O4: 1101388 | Q4: G-110000031-251015-0027-1 | R4: S10B.1.1423XL-01 | S4: -

Sheet 5720
A1: 贵州航天精工制造有限公司发货清单-5720 | N1: =VLOOKUP(I1,[6]数据!B:AE,30,FALSE) -> #N/A | O1: =VLOOKUP(I1,[6]数据!B:F,5,FALSE) -> #N/A | P1: =VLOOKUP('[6]5720'!I1,[6]数据!B:G,6,FALSE) -> #N/A
K2: 日期： | L2: 46139 | N2: =VLOOKUP(I2,[6]数据!B:AE,30,FALSE) -> #N/A | O2: =VLOOKUP(I2,[6]数据!B:F,5,FALSE) -> #N/A | P2: =VLOOKUP('[6]5720'!I2,[6]数据!B:G,6,FALSE) -> #N/A
A3: 序号 | B3: 标准号/图号 | C3: 规格 | D3: 表面处理 | E3: 发货数量 | F3: 单价 | G3: 发货金额 | H3: 批次号 | I3: 提货单号 | J3: 箱号 | K3: 清单备注 | N3: =VLOOKUP(I3,[6]数据!B:AE,30,FALSE) -> 客户采购订单编号 | O3: =VLOOKUP(I3,[6]数据!B:F,5,FALSE) -> 采用标准
A4: 1 | D4: 蓝色阳极化 | E4: 3630 | F4: 4 | G4: 14520 | H4: G2510-1747 | I4: 7101108206 | J4: 1# | K4: 合同号2025X1752，SK专项特急，12月15日必保，货发许陈，18255325276，安徽省芜湖市鸠江区南阳路国营芜湖机械厂" | M4: 1108206 | N4: G-110000029-251027-0102 | O4: Q/611S310-2010

Sheet 7102
A1: 贵州航天精工制造有限公司发货清单
A2: 收货单位：四川航天长征装备制造有限公司 联系人： 张晓迪 发货日期：2025.7.22
A3: 序号 | B3: 产品名称 | C3: 型号 | D3: 规格 | E3: 材质 | F3: 性能等级 | G3: 表面处理 | H3: 单位 | I3: 订货数量 | J3: 发货数量 | K3: 单价 | L3: 金额 | M3: 批次号 | N3: 办事处订单号 | O3: 运单号 | P3: 箱号 | Q3: 备注 | S3: 发货日期
A4: 1 | E4: Q235 | G4: Ep·Zn·c2C | H4: 件 | I4: 50 | J4: 50 | K4: 3 | L4: 150 | M4: G02507-023 | N4: G-100001932-250414-0405 | O4: SF1549653517994 | P4: 1# | R4: 7100977681 | S4: 977681
A5: 本次发货共计1箱，1项。(发货清单一式二份)

Sheet 贵州飞机
A1: 贵州航天精工发货清单--贵州飞机 | P1: 贵州飞机要求装箱单做好需要发给丁宇宇确认才能发货
A2: 序号 | B2: 产品名称 | C2: 型号 | D2: 规 格 | E2: 材 料 | F2: 性能等级 | G2: 表面处理 | H2: 发货数量 | I2: 批次号 | J2: 提货单号 | K2: 箱号 | L2: 合同号 | M2: 发货日期 | N2: 备注（试）
A3: 1 | D3: 21.6 | E3: 5870 | H3: 18 | I3: G2512-1428 | J3: 7101106631 | K3: 1# | L3: 贵飞采购-25-1-A13-0713 | M3: 46139 | O3: 1106631

Sheet 贵州红林
A1: 贵州航天精工发货清单--红林 | O1: 橡胶件务必按型号排序，再打印
A2: 序号 | B2: 产品名称 | C2: 型号 | D2: 规 格 | E2: 材 料 | F2: 性能等级 | G2: 表面处理 | H2: 发货数量 | I2: 批次号 | J2: 提货单号 | K2: 箱号 | L2: 发货日期 | M2: 备注
A3: 1 | D3: - | E3: 2A11 | F3: 0 | G3: 铬酸阳极化+螺纹和表面A涂MoS2 | H3: 2 | I3: G2512-1573 | J3: 7101108803 | K3: 1# | L3: 46140

Sheet 东安
A1: 装 箱 单-东安 | L1: 商发型号带有LNRGB/SNRGB批次号需要更改
A2: 提货单号 | B2: 批号 | C2: 采用标准 | D2: 规格 | E2: 材质 | F2: 表面处理 | G2: 性能等级 | H2: 提货数量 | I2: 箱号 | J2: 日期
A3: 7101108873 | B3: G2603-1397 | D3: - | E3: HNY300耐油石棉橡胶板 | H3: 30 | I3: 421 | J3: 46138 | L3: 急件发货，缺尺寸和首件包

Sheet 高精管轴
A1: 哈尔滨高精管轴装箱清单
A2: 序号 | B2: 物品名称 | C2: 采用标准 | D2: 规格 | E2: 材质 | F2: 性能等级 | G2: 表面处理 | H2: 批号 | I2: 已提货数量 | J2: 提货单号 | K2: 箱号 | L2: 发货日期 | N2: 有LNRGB/SNRGB开头的序列号要统一填写
A3: 1 | D3: - | E3: 14Cr17Ni2 | F3: 30-37HRC | G3: Ct·P | H3: G2603-0184 | I3: 103 | J3: 7101102910 | K3: 1# | L3: 46136 | M3: 1102910

Sheet 哈飞
A1: 贵州航天精工发货清单--哈飞
A2: 序号 | B2: 产品名称 | C2: 型号 | D2: 规 格 | E2: 材 料 | F2: 性能等级 | G2: 表面处理 | H2: 发货数量 | I2: 批次号 | J2: 提货单号 | K2: 箱号 | L2: 发货日期
A3: 1 | D3: G-404 | E3: 组件 | H3: 35 | I3: G2407-2196 | J3: 7101096972 | K3: 1# | L3: 46136 | M3: 1096972

Sheet 吉林航空维修
A1: 贵州航天精工发货清单--吉林航空维修
A2: 序号 | B2: 产品名称 | C2: 型号 | D2: 规 格 | E2: 材 料 | F2: 性能等级 | G2: 表面处理 | H2: 发货数量 | I2: 单价 | J2: 批次号 | K2: 提货单号 | L2: 箱号 | M2: 合同号 | N2: 发货日期
A3: 1 | D3: - | E3: FX-4 | H3: 15 | I3: 60 | J3: G2508-0158 | K3: 7101104978 | L3: 1# | M3: 型号:ZM17.5×2.5-FX-4，合同号JHC2025070815 | N3: 46139 | O3: 1104978

Sheet 四七二三
A1: 贵州航天精工发货清单--四七二三
A2: 序号 | B2: 产品名称 | C2: 型号 | D2: 规 格 | E2: 材 料 | F2: 性能等级 | G2: 表面处理 | H2: 发货数量 | I2: 批次号 | J2: 提货单号 | K2: 箱号 | L2: 合同号 | M2: 发货日期
A3: 1 | D3: - | E3: Cr17Ni2 | F3: d=3.5-3.8 | H3: 50 | I3: G2601-7539 | J3: 7101106816 | K3: 1# | L3: 合同号：26BF005GY003BJ | M3: 46137 | N3: 1106816

Sheet 江西昌河
A1: 贵州航天精工发货清单 | N1: 每次发货第一时间发表格给丁宇宇
A2: 序号 | B2: 产品名称 | C2: 型号 | D2: 规 格 | E2: 材 料 | F2: 性能等级 | G2: 表面处理 | H2: 发货数量 | I2: 批次号 | J2: 提货单号 | K2: 箱号 | L2: 发货日期 | M2: 备注
A3: 1 | D3: - | E3: 4340 | F3: 39-43HRC | G3: 镀镉,涂16醇 | H3: 23 | I3: G2403-0979 | J3: 7100945190 | K3: 1-1# | L3: 45906 | N3: 945190 | P3: 1100146600/10

Sheet 江西洪都
A1: 贵州航天精工发货清单---江西洪都
A2: 序号 | B2: 产品名称 | C2: 型号 | D2: 规 格 | E2: 材 料 | F2: 性能等级 | G2: 表面处理 | H2: 发货数量 | I2: 批次号 | J2: 提货单号 | K2: 合同号 | L2: 箱号 | M2: 发货日期 | N2: 备注
A3: 1 | D3: A-MJ5 | E3: A286 | F3: σb≥900MPa | G3: 钝化+二硫化钼 | H3: 902 | I3: G2410-1694 | J3: 7101095367 | L3: 1# | M3: 46122 | N3: X8 | O3: 1095367

Sheet 中科国晟
A1: 装 箱 单-中科国晟
A2: 提货单号 | B2: 批号 | C2: 采用标准 | D2: 规格 | E2: 材质 | F2: 表面处理 | G2: 性能等级 | H2: 提货数量 | I2: 箱号 | J2: 日期 | K2: 运单号
A3: 7101097860 | B3: G2510-1003 | D3: - | E3: 组件 | H3: 30 | I3: 1# | J3: 46122 | K3: 1387566170726 | L3: 1097860

Sheet 北京飞航捷迅物
A1: 装箱单 | J1: =710&K1 -> 710 | N1: =VLOOKUP(J1,[7]匹配!B:G,6,FALSE) -> #N/A | O1: =VLOOKUP(J1,[7]匹配!B:F,5,FALSE) -> #N/A
A2: 收货单位：北京飞航捷迅物资有限责任公司 | D2: 单据编号: | E2: 202604-0098 | F2: 货物总箱数： | G2: 1# | J2: =710&K2 -> 710 | N2: =VLOOKUP(J2,[7]匹配!B:G,6,FALSE) -> #N/A | O2: =VLOOKUP(J2,[7]匹配!B:F,5,FALSE) -> #N/A
A3: 供方名称 | B3: 贵州航天精工制造有限公司 | C3: 发货人 | D3: 周华伟 | E3: 制单日期 | F3: 46135 | G3: 收货人 | H3: 陈玲艳 | J3: =710&K3 -> 710 | N3: =VLOOKUP(J3,[7]匹配!B:G,6,FALSE) -> #N/A | O3: =VLOOKUP(J3,[7]匹配!B:F,5,FALSE) -> #N/A
A4: 序号 | B4: 采购文件编号 | C4: 规格型号 | D4: 质量等级 | E4: 批次 | F4: 生产日期 | G4: 数量 | H4: 备注 | I4: 箱号 | J4: =710&K4 -> 710 | N4: =VLOOKUP(J4,[7]匹配!B:G,6,FALSE) -> #N/A | O4: =VLOOKUP(J4,[7]匹配!B:F,5,FALSE) -> #N/A
A5: 1 | B5: 159_2025/X-11-0028 | E5: G2601-0486 | F5: 46126 | G5: 50 | I5: 1# | J5: 7101101459 | K5: 1101459 | N5: 14×110 | O5: HB1-704-
A6: 2 | B6: 2026/X-03-0053 | E6: G2603-1628 | F6: 46128 | G6: 51 | J6: 7101102722 | K6: 1102722 | N6: 15 | O6: HB3-16FD-
A7: 内装清单 证件资料 | J7: =L7&K7 -> 7100 | L7: =IF(K7>999999,710,7100) -> 7100 | N7: =VLOOKUP(J7,[8]匹配!B:G,6,FALSE) -> #N/A | O7: =VLOOKUP(J7,[8]匹配!B:F,5,FALSE) -> #N/A

Sheet 上海商用
A1: 商用航空发动机实物类交付物交接单
A2: 表单编号：GXJC123536-2026-0020
A3: 交付单位 | C3: 贵州航天精工制造有限公司 | E3: 型号: | I3: CJ1000A | J3: 订货单位 | L3: 上海商发制造 | O3: 接收单位 | Q3: 上海商发制造
A4: 对应验收单编号 | D4: SQ123536-2026-0033 | L4: 对应合同号 | O4: HT/SFZZ-2BTY·0008-2026
A5: 产品状态说明 | D5: □产品经商发验收通过。 □产品未经商发验收，按商发要求发往他处开展到货验收。
D6: □按商发要求发往其它单位开展测试改装/特定演示。 □其它：
A7: 序号 | B7: 零组件名称 | D7: 图号 | F7: 版次 | G7: 数量 | I7: 批次/顺序号 | K7: 合格证页数 | M7: 不合格品审理单/偏离单/代料单份数 | P7: 不合格品审理单/偏离单/代料单页数 | R7: 其它随带文件名称 | S7: 其它随带文件页数
A8: 1 | B8: 外套螺母 | F8: D | G8: 17 | I8: LNRGB26031978 | K8: 1 | M8: / | P8: / | R8: 试验报告/ 构型表/ 复验记录单/ | S8: 2
A9: 交付单位签字 ： 吕娅男 | H9: 订货单位签字： | N9: 接收单位签字：
A10: 日期：2026.4.21 | H10: 日期： | N10: 日期：
A11: 第 1 页/共 1 页
A12: 表单编号：SCM020-03 版次: C0
A13: 1. 本表单一式三份，随产品周转一份，供应商和验收方各留存一份，当使用线上流程时，无需纸质文件流转。
A14: 2.需由交付方、验收方和接收方三方对本表签字。
A15: 3. 本表单编号规则为“JJ（交接）-XXXXXX（交付方代码）-XXXXXX（接收方代码）-20XX（年代号）-XXXX（顺序号）”。

Sheet 沈阳飞机
A1: 日期 | B1: 2026.3.18 （产品已发何龙通知） | I1: 编号
A2: 收货单位 | D2: 沈飞公司器材保障部计划物流室 | I2: 发货单位 | L2: 贵州航天精工制造有限公司
A3: 供应员 | I3: 发货人
A4: 联系方式 | D4: - | I4: 联系方式
A5: 发货方式 | D5: 铁路专线 | G5: 中铁快运 | J5: 公路物流 | P5: 自提
A6: 序号 | B6: 到货日期 | C6: 计划编号 | D6: 材料牌号/规格 | E6: 炉批号 | F6: 合同号 | G6: 发货数量 | H6: 机型 | I6: 发货单位 | J6: 箱号 | K6: 三方报告 | L6: 试验件或同批次 | M6: 保管到日期 | N6: 生产日期 | O6: 名称 | P6: 路线 | Q6: 订货数量 | R6: 欠交数量 | S6: 有履约项可标记 | T6: 投产总数量 | U6: 备注 | V6: 物料编码 | W6: 订单号 | X6: 发货通知单 | Y6: 销售订单行
A7: 1 | E7: G2512-0518 | G7: 2267 | I7: 3536厂 | J7: G2168 | L7: 13 | T7: 3100 | V7: 000042944288076201 | W7: G-100011915-251128-0222 | X7: 7101082237 | Z7: 1082237 | AA7: 1100156599/20
A8: 发货人（签字）： | J8: 计划物流室（签字）：
A9: 材料采购室（签字）： | J9: 标准件中心（签字）：
A10: 发货人（签字）： | J10: 计划物流室（签字）：
A11: 材料采购室（签字）： | J11: 标准件中心（签字）：

Sheet 沈飞民用飞机
A1: 器材验收单 | P1: =7100&Q1 -> 7100
B2: 项目： | M2: 日期： | N2: 46137 | P2: =7100&Q2 -> 7100
A3: 供应商名称：贵州航天精工制造有限公司 | P3: =7100&Q3 -> 7100
A4: 序号 | B4: 合同号 | C4: 材料代码 | D4: 材料名称 | E4: 牌号 | F4: 规格 | G4: 技术规范 | H4: 批号 | I4: 单位 | J4: 订单数量 | K4: 到货数量 | L4: 实收数量 | M4: 计划价格 | N4: 金额 | O4: 备注
A5: 1 | B5: J11F26020 | H5: G2603-0640 | I5: pcs | K5: 70 | M5: 40.8 | N5: 2856 | P5: 7101105554 | Q5: 1105554 | R5: 1100161229/10
A6: 注：本单一式四联，白色联由采购留存，黄色联由财务留存，蓝色联和粉色联由库房留存。 | R6: #N/A

Sheet 潍柴动力
A1: 潍柴动力产品实验室仓库送货单
A2: 序号 | B2: 潍柴件号 | C2: 名称 | D2: 数量 | E2: 样件状态 | F2: 供方代码 | G2: 供方名称 | H2: 备注 | K2: 发货日期
A3: 1 | D3: 20 | E3: B01 | F3: 4M70 | G3: 贵州航天精工制造有限公司 | I3: 7100983925 | J3: 983925 | K3: 45863
A4: 收货地址：山东省潍坊市高新区潍安路与东风街路口北200米路西，潍柴工业园东南物流门智能物流中心10号门
A5: 收货人：黄晓娟15318986503（于朋）（并备注需求工程师名字）
A6: 送货方式：司机送货或顺丰快递，其他快递无法进入厂。
A7: 收货要求：零部件包装或零部件表面需按照图纸要求体现样件状态、供方代码、件号、批次号。

Sheet 西安莱特
A1: 装箱单 | H1: 务必检查型号和规格要连接在一起，但不能重复，切记！ | K1: =VLOOKUP(H1,[9]匹配!B:F,5,FALSE) -> #N/A | L1: =VLOOKUP(H1,[9]匹配!B:G,6,FALSE) -> #N/A
H2: =710&I2 -> 710 | J2: =VLOOKUP(H2,[9]匹配!B:AF,31,FALSE) -> #N/A | K2: =VLOOKUP(H2,[9]匹配!B:F,5,FALSE) -> #N/A | L2: =VLOOKUP(H2,[9]匹配!B:G,6,FALSE) -> #N/A
A3: 采购方：西安西航集团莱特航空制造技术有限公司 | E3: 装箱单号： | G3: HTJG24-XALT001 | H3: =710&I3 -> 710 | J3: =VLOOKUP(H3,[9]匹配!B:AF,31,FALSE) -> #N/A | K3: =VLOOKUP(H3,[9]匹配!B:F,5,FALSE) -> #N/A | L3: =VLOOKUP(H3,[9]匹配!B:G,6,FALSE) -> #N/A
A4: 地址：陕西省西安市经济技术开发区明光路光中综合保税区A区（莱特厂房） | E4: 发票号： | G4: 68678704/68668866 | H4: =710&I4 -> 710 | J4: =VLOOKUP(H4,[9]匹配!B:AF,31,FALSE) -> #N/A | K4: =VLOOKUP(H4,[9]匹配!B:F,5,FALSE) -> #N/A | L4: =VLOOKUP(H4,[9]匹配!B:G,6,FALSE) -> #N/A
E5: 日期： | G5: 46139 | H5: =710&I5 -> 710 | J5: =VLOOKUP(H5,[9]匹配!B:AF,31,FALSE) -> #N/A | K5: =VLOOKUP(H5,[9]匹配!B:F,5,FALSE) -> #N/A | L5: =VLOOKUP(H5,[9]匹配!B:G,6,FALSE) -> #N/A
H6: =710&I6 -> 710 | J6: =VLOOKUP(H6,[9]匹配!B:AF,31,FALSE) -> #N/A | K6: =VLOOKUP(H6,[9]匹配!B:F,5,FALSE) -> #N/A | L6: =VLOOKUP(H6,[9]匹配!B:G,6,FALSE) -> #N/A
A7: 销售方：贵州航天精工制造有限公司 | H7: =710&I7 -> 710 | J7: =VLOOKUP(H7,[9]匹配!B:AF,31,FALSE) -> #N/A | K7: =VLOOKUP(H7,[9]匹配!B:F,5,FALSE) -> #N/A | L7: =VLOOKUP(H7,[9]匹配!B:G,6,FALSE) -> #N/A
A8: 地址：贵州省遵义市红花岗区虾子镇 | H8: =710&I8 -> 710 | J8: =VLOOKUP(H8,[9]匹配!B:AF,31,FALSE) -> #N/A | K8: =VLOOKUP(H8,[9]匹配!B:F,5,FALSE) -> #N/A | L8: =VLOOKUP(H8,[9]匹配!B:G,6,FALSE) -> #N/A
A9: 序号 | B9: 产品名称 | C9: 型号/规格 | D9: 合同号 | E9: 数量（件） | F9: 单件净重（千克） | G9: 总净重（千克） | H9: =710&I9 -> 710 | J9: =VLOOKUP(H9,[9]匹配!B:AF,31,FALSE) -> #N/A | K9: =VLOOKUP(H9,[9]匹配!B:F,5,FALSE) -> #N/A | L9: =VLOOKUP(H9,[9]匹配!B:G,6,FALSE) -> #N/A
A10: 1 | B10: 球形导管接头 | D10: LT-CG-ZC-SF-2026190 | E10: 2 | F10: 0.0172 | G10: 0.0344 | H10: 7101105338 | I10: 1105338 | J10: 1100163643/50 | K10: SPE8004
A11: 2 | B11: 球形导管接头 | D11: LT-CG-ZC-SF-2026190 | E11: 2 | F11: 0.0172 | G11: 0.0344 | H11: 7101105338 | I11: 1105338 | J11: 1100163643/50 | K11: SPE8004
A12: 3 | B12: 球形导管接头 | D12: LT-CG-ZC-SF-2026190 | E12: 4 | F12: 0.0172 | G12: 0.0688 | H12: 7101105338 | I12: 1105338 | J12: 1100163643/50 | K12: SPE8004
A13: 4 | B13: 球形导管接头 | D13: LT-CG-ZC-SF-2026190 | E13: 2 | F13: 0.0172 | G13: 0.0344 | H13: 7101105338 | I13: 1105338 | J13: 1100163643/50 | K13: SPE8004
A14: 合计： | E14: 10 | H14: =710&I14 -> 710 | J14: =VLOOKUP(H14,[9]匹配!B:AF,31,FALSE) -> #N/A | K14: =VLOOKUP(H14,[9]匹配!B:F,5,FALSE) -> #N/A | L14: =VLOOKUP(H14,[9]匹配!B:G,6,FALSE) -> #N/A
A15: 箱数：共1纸箱 | H15: =710&I15 -> 710 | J15: =VLOOKUP(H15,[9]匹配!B:AF,31,FALSE) -> #N/A | K15: =VLOOKUP(H15,[9]匹配!B:F,5,FALSE) -> #N/A | L15: =VLOOKUP(H15,[9]匹配!B:G,6,FALSE) -> #N/A
A16: 合计：净重0.172 公斤，毛重1.25公斤 | H16: =710&I16 -> 710 | J16: =VLOOKUP(H16,[9]匹配!B:AF,31,FALSE) -> #N/A | K16: =VLOOKUP(H16,[9]匹配!B:F,5,FALSE) -> #N/A | L16: =VLOOKUP(H16,[9]匹配!B:G,6,FALSE) -> #N/A
A17: 贵州航天精工制造有限公司 | H17: =710&I17 -> 710 | J17: =VLOOKUP(H17,[9]匹配!B:AF,31,FALSE) -> #N/A | K17: =VLOOKUP(H17,[9]匹配!B:F,5,FALSE) -> #N/A | L17: =VLOOKUP(H17,[9]匹配!B:G,6,FALSE) -> #N/A
A18: 贵州省遵义市红花岗区虾子镇 | H18: =710&I18 -> 710 | J18: =VLOOKUP(H18,[9]匹配!B:AF,31,FALSE) -> #N/A | K18: =VLOOKUP(H18,[9]匹配!B:F,5,FALSE) -> #N/A | L18: =VLOOKUP(H18,[9]匹配!B:G,6,FALSE) -> #N/A
A19: TEL:0851-28693536 | H19: =710&I19 -> 710 | J19: =VLOOKUP(H19,[9]匹配!B:AF,31,FALSE) -> #N/A | K19: =VLOOKUP(H19,[9]匹配!B:F,5,FALSE) -> #N/A | L19: =VLOOKUP(H19,[9]匹配!B:G,6,FALSE) -> #N/A

Sheet 西安宇立
A1: 装箱清单--西安宇立航空科技 | N1: =710&O1 -> 710
A2: 序号 | B2: 产品名称 | C2: 标准号 | D2: 规格 | E2: 材料 | F2: 性能等级 | G2: 表面处理 | H2: 数量 | I2: 批次号 | J2: 单价 | K2: 金额 | L2: 合同号 | M2: 箱号 | N2: =710&O2 -> 710
A3: 1 | D3: 1.5×30 | E3: 2A12 | F3: σb≥390MPa | G3: Et·A(S)·Cs | H3: 5 | I3: G2107-2152 | J3: 7.2 | K3: 36 | L3: 发宇立-马静，4.07订货，现货：G2107-2152 | M3: 1# | N3: 7101098611 | O3: 1098611

Sheet 西安飞机
A1: 航天精工股份有限公司(贵州)发货汇总清单 | Q1: =VLOOKUP(N1,[10]匹配数据!B:AF,31,FALSE) -> #N/A
A2: 发货日期： | D2: 46134 | K2: 使用部门：库房 | Q2: =VLOOKUP(N2,[10]匹配数据!B:AF,31,FALSE) -> #N/A
A3: 序号 | B3: 标准件号 | D3: 交付数量 | E3: 批次号 | F3: 订单数量 | G3: 生产日期 | H3: 表面处理 | I3: 橡胶件保管周期 | J3: 试验件及报告携带情况 | K3: 客户订单号（原订单号） | L3: 客户计划号 | M3: 箱号 | N3: 提货单号 | Q3: =VLOOKUP(N3,[10]匹配数据!B:AF,31,FALSE) -> 销售订单行
A4: 1 | D4: 186 | E4: G2602-0264 | F4: 550 | G4: 46132 | J4: 资料齐全 | K4: G-100003643-250108-0014 | L4: 11552303202501-002 | M4: 1# | N4: 7101104702 | O4: 1104702 | Q4: 1100140058/20

Sheet 运载火箭
A1: 运载火箭发货清单-2026.4.21产品已发
A2: 序号 | B2: 提货单 | C2: 计划号 | D2: 名称 | E2: 型号 | F2: 规格 | G2: 数量（件） | H2: 箱号 | I2: 盒号 | J2: 组批号 | K2: 前期是否发过货 | L2: 备注 | P2: 试验件
A3: 1 | B3: 7101098638 | C3: G2509-1288 | F3: 5×8 | G3: 230 | H3: 1# | I3: 1-1 | J3: HP2512-002 | K3: 否 | M3: 1098638 | P3: 12

Sheet 重庆红宇
A1: 贵州航天精工发货清单-重庆红宇 | Q1: 贵州航天精工发货清单 | AG1: 贵州航天精工发货清单 | AW1: 贵州航天精工发货清单 | BM1: 贵州航天精工发货清单 | CC1: 贵州航天精工发货清单 | CS1: 贵州航天精工发货清单 | DI1: 贵州航天精工发货清单 | DY1: 贵州航天精工发货清单 | EO1: 贵州航天精工发货清单 | FE1: 贵州航天精工发货清单 | FU1: 贵州航天精工发货清单 | GK1: 贵州航天精工发货清单 | HA1: 贵州航天精工发货清单 | HQ1: 贵州航天精工发货清单 | IG1: 贵州航天精工发货清单 | IW1: 贵州航天精工发货清单 | JM1: 贵州航天精工发货清单 | KC1: 贵州航天精工发货清单 | KS1: 贵州航天精工发货清单 | LI1: 贵州航天精工发货清单 | LY1: 贵州航天精工发货清单 | MO1: 贵州航天精工发货清单 | NE1: 贵州航天精工发货清单 | NU1: 贵州航天精工发货清单 | OK1: 贵州航天精工发货清单 | PA1: 贵州航天精工发货清单 | PQ1: 贵州航天精工发货清单 | QG1: 贵州航天精工发货清单 | QW1: 贵州航天精工发货清单 | RM1: 贵州航天精工发货清单 | SC1: 贵州航天精工发货清单 | SS1: 贵州航天精工发货清单 | TI1: 贵州航天精工发货清单 | TY1: 贵州航天精工发货清单 | UO1: 贵州航天精工发货清单 | VE1: 贵州航天精工发货清单 | VU1: 贵州航天精工发货清单 | WK1: 贵州航天精工发货清单 | XA1: 贵州航天精工发货清单 | XQ1: 贵州航天精工发货清单 | YG1: 贵州航天精工发货清单 | YW1: 贵州航天精工发货清单 | ZM1: 贵州航天精工发货清单 | AAC1: 贵州航天精工发货清单 | AAS1: 贵州航天精工发货清单 | ABI1: 贵州航天精工发货清单 | ABY1: 贵州航天精工发货清单 | ACO1: 贵州航天精工发货清单 | ADE1: 贵州航天精工发货清单 | ADU1: 贵州航天精工发货清单 | AEK1: 贵州航天精工发货清单 | AFA1: 贵州航天精工发货清单 | AFQ1: 贵州航天精工发货清单 | AGG1: 贵州航天精工发货清单 | AGW1: 贵州航天精工发货清单 | AHM1: 贵州航天精工发货清单 | AIC1: 贵州航天精工发货清单 | AIS1: 贵州航天精工发货清单 | AJI1: 贵州航天精工发货清单 | AJY1: 贵州航天精工发货清单 | AKO1: 贵州航天精工发货清单 | ALE1: 贵州航天精工发货清单 | ALU1: 贵州航天精工发货清单 | AMK1: 贵州航天精工发货清单 | ANA1: 贵州航天精工发货清单 | ANQ1: 贵州航天精工发货清单 | AOG1: 贵州航天精工发货清单 | AOW1: 贵州航天精工发货清单 | APM1: 贵州航天精工发货清单 | AQC1: 贵州航天精工发货清单 | AQS1: 贵州航天精工发货清单 | ARI1: 贵州航天精工发货清单 | ARY1: 贵州航天精工发货清单 | ASO1: 贵州航天精工发货清单 | ATE1: 贵州航天精工发货清单 | ATU1: 贵州航天精工发货清单 | AUK1: 贵州航天精工发货清单 | AVA1: 贵州航天精工发货清单 | AVQ1: 贵州航天精工发货清单 | AWG1: 贵州航天精工发货清单 | AWW1: 贵州航天精工发货清单 | AXM1: 贵州航天精工发货清单 | AYC1: 贵州航天精工发货清单 | AYS1: 贵州航天精工发货清单 | AZI1: 贵州航天精工发货清单 | AZY1: 贵州航天精工发货清单 | BAO1: 贵州航天精工发货清单 | BBE1: 贵州航天精工发货清单 | BBU1: 贵州航天精工发货清单 | BCK1: 贵州航天精工发货清单 | BDA1: 贵州航天精工发货清单 | BDQ1: 贵州航天精工发货清单 | BEG1: 贵州航天精工发货清单 | BEW1: 贵州航天精工发货清单 | BFM1: 贵州航天精工发货清单 | BGC1: 贵州航天精工发货清单 | BGS1: 贵州航天精工发货清单 | BHI1: 贵州航天精工发货清单 | BHY1: 贵州航天精工发货清单 | BIO1: 贵州航天精工发货清单 | BJE1: 贵州航天精工发货清单 | BJU1: 贵州航天精工发货清单 | BKK1: 贵州航天精工发货清单 | BLA1: 贵州航天精工发货清单 | BLQ1: 贵州航天精工发货清单 | BMG1: 贵州航天精工发货清单 | BMW1: 贵州航天精工发货清单 | BNM1: 贵州航天精工发货清单 | BOC1: 贵州航天精工发货清单 | BOS1: 贵州航天精工发货清单 | BPI1: 贵州航天精工发货清单 | BPY1: 贵州航天精工发货清单 | BQO1: 贵州航天精工发货清单 | BRE1: 贵州航天精工发货清单 | BRU1: 贵州航天精工发货清单 | BSK1: 贵州航天精工发货清单 | BTA1: 贵州航天精工发货清单 | BTQ1: 贵州航天精工发货清单 | BUG1: 贵州航天精工发货清单 | BUW1: 贵州航天精工发货清单 | BVM1: 贵州航天精工发货清单 | BWC1: 贵州航天精工发货清单 | BWS1: 贵州航天精工发货清单 | BXI1: 贵州航天精工发货清单 | BXY1: 贵州航天精工发货清单 | BYO1: 贵州航天精工发货清单 | BZE1: 贵州航天精工发货清单 | BZU1: 贵州航天精工发货清单 | CAK1: 贵州航天精工发货清单 | CBA1: 贵州航天精工发货清单 | CBQ1: 贵州航天精工发货清单 | CCG1: 贵州航天精工发货清单 | CCW1: 贵州航天精工发货清单 | CDM1: 贵州航天精工发货清单 | CEC1: 贵州航天精工发货清单 | CES1: 贵州航天精工发货清单 | CFI1: 贵州航天精工发货清单 | CFY1: 贵州航天精工发货清单 | CGO1: 贵州航天精工发货清单 | CHE1: 贵州航天精工发货清单 | CHU1: 贵州航天精工发货清单 | CIK1: 贵州航天精工发货清单 | CJA1: 贵州航天精工发货清单 | CJQ1: 贵州航天精工发货清单 | CKG1: 贵州航天精工发货清单 | CKW1: 贵州航天精工发货清单 | CLM1: 贵州航天精工发货清单 | CMC1: 贵州航天精工发货清单 | CMS1: 贵州航天精工发货清单 | CNI1: 贵州航天精工发货清单 | CNY1: 贵州航天精工发货清单 | COO1: 贵州航天精工发货清单 | CPE1: 贵州航天精工发货清单 | CPU1: 贵州航天精工发货清单 | CQK1: 贵州航天精工发货清单 | CRA1: 贵州航天精工发货清单 | CRQ1: 贵州航天精工发货清单 | CSG1: 贵州航天精工发货清单 | CSW1: 贵州航天精工发货清单 | CTM1: 贵州航天精工发货清单 | CUC1: 贵州航天精工发货清单 | CUS1: 贵州航天精工发货清单 | CVI1: 贵州航天精工发货清单 | CVY1: 贵州航天精工发货清单 | CWO1: 贵州航天精工发货清单 | CXE1: 贵州航天精工发货清单 | CXU1: 贵州航天精工发货清单 | CYK1: 贵州航天精工发货清单 | CZA1: 贵州航天精工发货清单 | CZQ1: 贵州航天精工发货清单 | DAG1: 贵州航天精工发货清单 | DAW1: 贵州航天精工发货清单 | DBM1: 贵州航天精工发货清单 | DCC1: 贵州航天精工发货清单 | DCS1: 贵州航天精工发货清单 | DDI1: 贵州航天精工发货清单 | DDY1: 贵州航天精工发货清单 | DEO1: 贵州航天精工发货清单 | DFE1: 贵州航天精工发货清单 | DFU1: 贵州航天精工发货清单 | DGK1: 贵州航天精工发货清单 | DHA1: 贵州航天精工发货清单 | DHQ1: 贵州航天精工发货清单 | DIG1: 贵州航天精工发货清单 | DIW1: 贵州航天精工发货清单 | DJM1: 贵州航天精工发货清单 | DKC1: 贵州航天精工发货清单 | DKS1: 贵州航天精工发货清单 | DLI1: 贵州航天精工发货清单 | DLY1: 贵州航天精工发货清单 | DMO1: 贵州航天精工发货清单 | DNE1: 贵州航天精工发货清单 | DNU1: 贵州航天精工发货清单 | DOK1: 贵州航天精工发货清单 | DPA1: 贵州航天精工发货清单 | DPQ1: 贵州航天精工发货清单 | DQG1: 贵州航天精工发货清单 | DQW1: 贵州航天精工发货清单 | DRM1: 贵州航天精工发货清单 | DSC1: 贵州航天精工发货清单 | DSS1: 贵州航天精工发货清单 | DTI1: 贵州航天精工发货清单 | DTY1: 贵州航天精工发货清单 | DUO1: 贵州航天精工发货清单 | DVE1: 贵州航天精工发货清单 | DVU1: 贵州航天精工发货清单 | DWK1: 贵州航天精工发货清单 | DXA1: 贵州航天精工发货清单 | DXQ1: 贵州航天精工发货清单 | DYG1: 贵州航天精工发货清单 | DYW1: 贵州航天精工发货清单 | DZM1: 贵州航天精工发货清单 | EAC1: 贵州航天精工发货清单 | EAS1: 贵州航天精工发货清单 | EBI1: 贵州航天精工发货清单 | EBY1: 贵州航天精工发货清单 | ECO1: 贵州航天精工发货清单 | EDE1: 贵州航天精工发货清单 | EDU1: 贵州航天精工发货清单 | EEK1: 贵州航天精工发货清单 | EFA1: 贵州航天精工发货清单 | EFQ1: 贵州航天精工发货清单 | EGG1: 贵州航天精工发货清单 | EGW1: 贵州航天精工发货清单 | EHM1: 贵州航天精工发货清单 | EIC1: 贵州航天精工发货清单 | EIS1: 贵州航天精工发货清单 | EJI1: 贵州航天精工发货清单 | EJY1: 贵州航天精工发货清单 | EKO1: 贵州航天精工发货清单 | ELE1: 贵州航天精工发货清单 | ELU1: 贵州航天精工发货清单 | EMK1: 贵州航天精工发货清单 | ENA1: 贵州航天精工发货清单 | ENQ1: 贵州航天精工发货清单 | EOG1: 贵州航天精工发货清单 | EOW1: 贵州航天精工发货清单 | EPM1: 贵州航天精工发货清单 | EQC1: 贵州航天精工发货清单 | EQS1: 贵州航天精工发货清单 | ERI1: 贵州航天精工发货清单 | ERY1: 贵州航天精工发货清单 | ESO1: 贵州航天精工发货清单 | ETE1: 贵州航天精工发货清单 | ETU1: 贵州航天精工发货清单 | EUK1: 贵州航天精工发货清单 | EVA1: 贵州航天精工发货清单 | EVQ1: 贵州航天精工发货清单 | EWG1: 贵州航天精工发货清单 | EWW1: 贵州航天精工发货清单 | EXM1: 贵州航天精工发货清单 | EYC1: 贵州航天精工发货清单 | EYS1: 贵州航天精工发货清单 | EZI1: 贵州航天精工发货清单 | EZY1: 贵州航天精工发货清单 | FAO1: 贵州航天精工发货清单 | FBE1: 贵州航天精工发货清单 | FBU1: 贵州航天精工发货清单 | FCK1: 贵州航天精工发货清单 | FDA1: 贵州航天精工发货清单 | FDQ1: 贵州航天精工发货清单 | FEG1: 贵州航天精工发货清单 | FEW1: 贵州航天精工发货清单 | FFM1: 贵州航天精工发货清单 | FGC1: 贵州航天精工发货清单 | FGS1: 贵州航天精工发货清单 | FHI1: 贵州航天精工发货清单 | FHY1: 贵州航天精工发货清单 | FIO1: 贵州航天精工发货清单 | FJE1: 贵州航天精工发货清单 | FJU1: 贵州航天精工发货清单 | FKK1: 贵州航天精工发货清单 | FLA1: 贵州航天精工发货清单 | FLQ1: 贵州航天精工发货清单 | FMG1: 贵州航天精工发货清单 | FMW1: 贵州航天精工发货清单 | FNM1: 贵州航天精工发货清单 | FOC1: 贵州航天精工发货清单 | FOS1: 贵州航天精工发货清单 | FPI1: 贵州航天精工发货清单 | FPY1: 贵州航天精工发货清单 | FQO1: 贵州航天精工发货清单 | FRE1: 贵州航天精工发货清单 | FRU1: 贵州航天精工发货清单 | FSK1: 贵州航天精工发货清单 | FTA1: 贵州航天精工发货清单 | FTQ1: 贵州航天精工发货清单 | FUG1: 贵州航天精工发货清单 | FUW1: 贵州航天精工发货清单 | FVM1: 贵州航天精工发货清单 | FWC1: 贵州航天精工发货清单 | FWS1: 贵州航天精工发货清单 | FXI1: 贵州航天精工发货清单 | FXY1: 贵州航天精工发货清单 | FYO1: 贵州航天精工发货清单 | FZE1: 贵州航天精工发货清单 | FZU1: 贵州航天精工发货清单 | GAK1: 贵州航天精工发货清单 | GBA1: 贵州航天精工发货清单 | GBQ1: 贵州航天精工发货清单 | GCG1: 贵州航天精工发货清单 | GCW1: 贵州航天精工发货清单 | GDM1: 贵州航天精工发货清单 | GEC1: 贵州航天精工发货清单 | GES1: 贵州航天精工发货清单 | GFI1: 贵州航天精工发货清单 | GFY1: 贵州航天精工发货清单 | GGO1: 贵州航天精工发货清单 | GHE1: 贵州航天精工发货清单 | GHU1: 贵州航天精工发货清单 | GIK1: 贵州航天精工发货清单 | GJA1: 贵州航天精工发货清单 | GJQ1: 贵州航天精工发货清单 | GKG1: 贵州航天精工发货清单 | GKW1: 贵州航天精工发货清单 | GLM1: 贵州航天精工发货清单 | GMC1: 贵州航天精工发货清单 | GMS1: 贵州航天精工发货清单 | GNI1: 贵州航天精工发货清单 | GNY1: 贵州航天精工发货清单 | GOO1: 贵州航天精工发货清单 | GPE1: 贵州航天精工发货清单 | GPU1: 贵州航天精工发货清单 | GQK1: 贵州航天精工发货清单 | GRA1: 贵州航天精工发货清单 | GRQ1: 贵州航天精工发货清单 | GSG1: 贵州航天精工发货清单 | GSW1: 贵州航天精工发货清单 | GTM1: 贵州航天精工发货清单 | GUC1: 贵州航天精工发货清单 | GUS1: 贵州航天精工发货清单 | GVI1: 贵州航天精工发货清单 | GVY1: 贵州航天精工发货清单 | GWO1: 贵州航天精工发货清单 | GXE1: 贵州航天精工发货清单 | GXU1: 贵州航天精工发货清单 | GYK1: 贵州航天精工发货清单 | GZA1: 贵州航天精工发货清单 | GZQ1: 贵州航天精工发货清单 | HAG1: 贵州航天精工发货清单 | HAW1: 贵州航天精工发货清单 | HBM1: 贵州航天精工发货清单 | HCC1: 贵州航天精工发货清单 | HCS1: 贵州航天精工发货清单 | HDI1: 贵州航天精工发货清单 | HDY1: 贵州航天精工发货清单 | HEO1: 贵州航天精工发货清单 | HFE1: 贵州航天精工发货清单 | HFU1: 贵州航天精工发货清单 | HGK1: 贵州航天精工发货清单 | HHA1: 贵州航天精工发货清单 | HHQ1: 贵州航天精工发货清单 | HIG1: 贵州航天精工发货清单 | HIW1: 贵州航天精工发货清单 | HJM1: 贵州航天精工发货清单 | HKC1: 贵州航天精工发货清单 | HKS1: 贵州航天精工发货清单 | HLI1: 贵州航天精工发货清单 | HLY1: 贵州航天精工发货清单 | HMO1: 贵州航天精工发货清单 | HNE1: 贵州航天精工发货清单 | HNU1: 贵州航天精工发货清单 | HOK1: 贵州航天精工发货清单 | HPA1: 贵州航天精工发货清单 | HPQ1: 贵州航天精工发货清单 | HQG1: 贵州航天精工发货清单 | HQW1: 贵州航天精工发货清单 | HRM1: 贵州航天精工发货清单 | HSC1: 贵州航天精工发货清单 | HSS1: 贵州航天精工发货清单 | HTI1: 贵州航天精工发货清单 | HTY1: 贵州航天精工发货清单 | HUO1: 贵州航天精工发货清单 | HVE1: 贵州航天精工发货清单 | HVU1: 贵州航天精工发货清单 | HWK1: 贵州航天精工发货清单 | HXA1: 贵州航天精工发货清单 | HXQ1: 贵州航天精工发货清单 | HYG1: 贵州航天精工发货清单 | HYW1: 贵州航天精工发货清单 | HZM1: 贵州航天精工发货清单 | IAC1: 贵州航天精工发货清单 | IAS1: 贵州航天精工发货清单 | IBI1: 贵州航天精工发货清单 | IBY1: 贵州航天精工发货清单 | ICO1: 贵州航天精工发货清单 | IDE1: 贵州航天精工发货清单 | IDU1: 贵州航天精工发货清单 | IEK1: 贵州航天精工发货清单 | IFA1: 贵州航天精工发货清单 | IFQ1: 贵州航天精工发货清单 | IGG1: 贵州航天精工发货清单 | IGW1: 贵州航天精工发货清单 | IHM1: 贵州航天精工发货清单 | IIC1: 贵州航天精工发货清单 | IIS1: 贵州航天精工发货清单 | IJI1: 贵州航天精工发货清单 | IJY1: 贵州航天精工发货清单 | IKO1: 贵州航天精工发货清单 | ILE1: 贵州航天精工发货清单 | ILU1: 贵州航天精工发货清单 | IMK1: 贵州航天精工发货清单 | INA1: 贵州航天精工发货清单 | INQ1: 贵州航天精工发货清单 | IOG1: 贵州航天精工发货清单 | IOW1: 贵州航天精工发货清单 | IPM1: 贵州航天精工发货清单 | IQC1: 贵州航天精工发货清单 | IQS1: 贵州航天精工发货清单 | IRI1: 贵州航天精工发货清单 | IRY1: 贵州航天精工发货清单 | ISO1: 贵州航天精工发货清单 | ITE1: 贵州航天精工发货清单 | ITU1: 贵州航天精工发货清单 | IUK1: 贵州航天精工发货清单 | IVA1: 贵州航天精工发货清单 | IVQ1: 贵州航天精工发货清单 | IWG1: 贵州航天精工发货清单 | IWW1: 贵州航天精工发货清单 | IXM1: 贵州航天精工发货清单 | IYC1: 贵州航天精工发货清单 | IYS1: 贵州航天精工发货清单 | IZI1: 贵州航天精工发货清单 | IZY1: 贵州航天精工发货清单 | JAO1: 贵州航天精工发货清单 | JBE1: 贵州航天精工发货清单 | JBU1: 贵州航天精工发货清单 | JCK1: 贵州航天精工发货清单 | JDA1: 贵州航天精工发货清单 | JDQ1: 贵州航天精工发货清单 | JEG1: 贵州航天精工发货清单 | JEW1: 贵州航天精工发货清单 | JFM1: 贵州航天精工发货清单 | JGC1: 贵州航天精工发货清单 | JGS1: 贵州航天精工发货清单 | JHI1: 贵州航天精工发货清单 | JHY1: 贵州航天精工发货清单 | JIO1: 贵州航天精工发货清单 | JJE1: 贵州航天精工发货清单 | JJU1: 贵州航天精工发货清单 | JKK1: 贵州航天精工发货清单 | JLA1: 贵州航天精工发货清单 | JLQ1: 贵州航天精工发货清单 | JMG1: 贵州航天精工发货清单 | JMW1: 贵州航天精工发货清单 | JNM1: 贵州航天精工发货清单 | JOC1: 贵州航天精工发货清单 | JOS1: 贵州航天精工发货清单 | JPI1: 贵州航天精工发货清单 | JPY1: 贵州航天精工发货清单 | JQO1: 贵州航天精工发货清单 | JRE1: 贵州航天精工发货清单 | JRU1: 贵州航天精工发货清单 | JSK1: 贵州航天精工发货清单 | JTA1: 贵州航天精工发货清单 | JTQ1: 贵州航天精工发货清单 | JUG1: 贵州航天精工发货清单 | JUW1: 贵州航天精工发货清单 | JVM1: 贵州航天精工发货清单 | JWC1: 贵州航天精工发货清单 | JWS1: 贵州航天精工发货清单 | JXI1: 贵州航天精工发货清单 | JXY1: 贵州航天精工发货清单 | JYO1: 贵州航天精工发货清单 | JZE1: 贵州航天精工发货清单 | JZU1: 贵州航天精工发货清单 | KAK1: 贵州航天精工发货清单 | KBA1: 贵州航天精工发货清单 | KBQ1: 贵州航天精工发货清单 | KCG1: 贵州航天精工发货清单 | KCW1: 贵州航天精工发货清单 | KDM1: 贵州航天精工发货清单 | KEC1: 贵州航天精工发货清单 | KES1: 贵州航天精工发货清单 | KFI1: 贵州航天精工发货清单 | KFY1: 贵州航天精工发货清单 | KGO1: 贵州航天精工发货清单 | KHE1: 贵州航天精工发货清单 | KHU1: 贵州航天精工发货清单 | KIK1: 贵州航天精工发货清单 | KJA1: 贵州航天精工发货清单 | KJQ1: 贵州航天精工发货清单 | KKG1: 贵州航天精工发货清单 | KKW1: 贵州航天精工发货清单 | KLM1: 贵州航天精工发货清单 | KMC1: 贵州航天精工发货清单 | KMS1: 贵州航天精工发货清单 | KNI1: 贵州航天精工发货清单 | KNY1: 贵州航天精工发货清单 | KOO1: 贵州航天精工发货清单 | KPE1: 贵州航天精工发货清单 | KPU1: 贵州航天精工发货清单 | KQK1: 贵州航天精工发货清单 | KRA1: 贵州航天精工发货清单 | KRQ1: 贵州航天精工发货清单 | KSG1: 贵州航天精工发货清单 | KSW1: 贵州航天精工发货清单 | KTM1: 贵州航天精工发货清单 | KUC1: 贵州航天精工发货清单 | KUS1: 贵州航天精工发货清单 | KVI1: 贵州航天精工发货清单 | KVY1: 贵州航天精工发货清单 | KWO1: 贵州航天精工发货清单 | KXE1: 贵州航天精工发货清单 | KXU1: 贵州航天精工发货清单 | KYK1: 贵州航天精工发货清单 | KZA1: 贵州航天精工发货清单 | KZQ1: 贵州航天精工发货清单 | LAG1: 贵州航天精工发货清单 | LAW1: 贵州航天精工发货清单 | LBM1: 贵州航天精工发货清单 | LCC1: 贵州航天精工发货清单 | LCS1: 贵州航天精工发货清单 | LDI1: 贵州航天精工发货清单 | LDY1: 贵州航天精工发货清单 | LEO1: 贵州航天精工发货清单 | LFE1: 贵州航天精工发货清单 | LFU1: 贵州航天精工发货清单 | LGK1: 贵州航天精工发货清单 | LHA1: 贵州航天精工发货清单 | LHQ1: 贵州航天精工发货清单 | LIG1: 贵州航天精工发货清单 | LIW1: 贵州航天精工发货清单 | LJM1: 贵州航天精工发货清单 | LKC1: 贵州航天精工发货清单 | LKS1: 贵州航天精工发货清单 | LLI1: 贵州航天精工发货清单 | LLY1: 贵州航天精工发货清单 | LMO1: 贵州航天精工发货清单 | LNE1: 贵州航天精工发货清单 | LNU1: 贵州航天精工发货清单 | LOK1: 贵州航天精工发货清单 | LPA1: 贵州航天精工发货清单 | LPQ1: 贵州航天精工发货清单 | LQG1: 贵州航天精工发货清单 | LQW1: 贵州航天精工发货清单 | LRM1: 贵州航天精工发货清单 | LSC1: 贵州航天精工发货清单 | LSS1: 贵州航天精工发货清单 | LTI1: 贵州航天精工发货清单 | LTY1: 贵州航天精工发货清单 | LUO1: 贵州航天精工发货清单 | LVE1: 贵州航天精工发货清单 | LVU1: 贵州航天精工发货清单 | LWK1: 贵州航天精工发货清单 | LXA1: 贵州航天精工发货清单 | LXQ1: 贵州航天精工发货清单 | LYG1: 贵州航天精工发货清单 | LYW1: 贵州航天精工发货清单 | LZM1: 贵州航天精工发货清单 | MAC1: 贵州航天精工发货清单 | MAS1: 贵州航天精工发货清单 | MBI1: 贵州航天精工发货清单 | MBY1: 贵州航天精工发货清单 | MCO1: 贵州航天精工发货清单 | MDE1: 贵州航天精工发货清单 | MDU1: 贵州航天精工发货清单 | MEK1: 贵州航天精工发货清单 | MFA1: 贵州航天精工发货清单 | MFQ1: 贵州航天精工发货清单 | MGG1: 贵州航天精工发货清单 | MGW1: 贵州航天精工发货清单 | MHM1: 贵州航天精工发货清单 | MIC1: 贵州航天精工发货清单 | MIS1: 贵州航天精工发货清单 | MJI1: 贵州航天精工发货清单 | MJY1: 贵州航天精工发货清单 | MKO1: 贵州航天精工发货清单 | MLE1: 贵州航天精工发货清单 | MLU1: 贵州航天精工发货清单 | MMK1: 贵州航天精工发货清单 | MNA1: 贵州航天精工发货清单 | MNQ1: 贵州航天精工发货清单 | MOG1: 贵州航天精工发货清单 | MOW1: 贵州航天精工发货清单 | MPM1: 贵州航天精工发货清单 | MQC1: 贵州航天精工发货清单 | MQS1: 贵州航天精工发货清单 | MRI1: 贵州航天精工发货清单 | MRY1: 贵州航天精工发货清单 | MSO1: 贵州航天精工发货清单 | MTE1: 贵州航天精工发货清单 | MTU1: 贵州航天精工发货清单 | MUK1: 贵州航天精工发货清单 | MVA1: 贵州航天精工发货清单 | MVQ1: 贵州航天精工发货清单 | MWG1: 贵州航天精工发货清单 | MWW1: 贵州航天精工发货清单 | MXM1: 贵州航天精工发货清单 | MYC1: 贵州航天精工发货清单 | MYS1: 贵州航天精工发货清单 | MZI1: 贵州航天精工发货清单 | MZY1: 贵州航天精工发货清单 | NAO1: 贵州航天精工发货清单 | NBE1: 贵州航天精工发货清单 | NBU1: 贵州航天精工发货清单 | NCK1: 贵州航天精工发货清单 | NDA1: 贵州航天精工发货清单 | NDQ1: 贵州航天精工发货清单 | NEG1: 贵州航天精工发货清单 | NEW1: 贵州航天精工发货清单 | NFM1: 贵州航天精工发货清单 | NGC1: 贵州航天精工发货清单 | NGS1: 贵州航天精工发货清单 | NHI1: 贵州航天精工发货清单 | NHY1: 贵州航天精工发货清单 | NIO1: 贵州航天精工发货清单 | NJE1: 贵州航天精工发货清单 | NJU1: 贵州航天精工发货清单 | NKK1: 贵州航天精工发货清单 | NLA1: 贵州航天精工发货清单 | NLQ1: 贵州航天精工发货清单 | NMG1: 贵州航天精工发货清单 | NMW1: 贵州航天精工发货清单 | NNM1: 贵州航天精工发货清单 | NOC1: 贵州航天精工发货清单 | NOS1: 贵州航天精工发货清单 | NPI1: 贵州航天精工发货清单 | NPY1: 贵州航天精工发货清单 | NQO1: 贵州航天精工发货清单 | NRE1: 贵州航天精工发货清单 | NRU1: 贵州航天精工发货清单 | NSK1: 贵州航天精工发货清单 | NTA1: 贵州航天精工发货清单 | NTQ1: 贵州航天精工发货清单 | NUG1: 贵州航天精工发货清单 | NUW1: 贵州航天精工发货清单 | NVM1: 贵州航天精工发货清单 | NWC1: 贵州航天精工发货清单 | NWS1: 贵州航天精工发货清单 | NXI1: 贵州航天精工发货清单 | NXY1: 贵州航天精工发货清单 | NYO1: 贵州航天精工发货清单 | NZE1: 贵州航天精工发货清单 | NZU1: 贵州航天精工发货清单 | OAK1: 贵州航天精工发货清单 | OBA1: 贵州航天精工发货清单 | OBQ1: 贵州航天精工发货清单 | OCG1: 贵州航天精工发货清单 | OCW1: 贵州航天精工发货清单 | ODM1: 贵州航天精工发货清单 | OEC1: 贵州航天精工发货清单 | OES1: 贵州航天精工发货清单 | OFI1: 贵州航天精工发货清单 | OFY1: 贵州航天精工发货清单 | OGO1: 贵州航天精工发货清单 | OHE1: 贵州航天精工发货清单 | OHU1: 贵州航天精工发货清单 | OIK1: 贵州航天精工发货清单 | OJA1: 贵州航天精工发货清单 | OJQ1: 贵州航天精工发货清单 | OKG1: 贵州航天精工发货清单 | OKW1: 贵州航天精工发货清单 | OLM1: 贵州航天精工发货清单 | OMC1: 贵州航天精工发货清单 | OMS1: 贵州航天精工发货清单 | ONI1: 贵州航天精工发货清单 | ONY1: 贵州航天精工发货清单 | OOO1: 贵州航天精工发货清单 | OPE1: 贵州航天精工发货清单 | OPU1: 贵州航天精工发货清单 | OQK1: 贵州航天精工发货清单 | ORA1: 贵州航天精工发货清单 | ORQ1: 贵州航天精工发货清单 | OSG1: 贵州航天精工发货清单 | OSW1: 贵州航天精工发货清单 | OTM1: 贵州航天精工发货清单 | OUC1: 贵州航天精工发货清单 | OUS1: 贵州航天精工发货清单 | OVI1: 贵州航天精工发货清单 | OVY1: 贵州航天精工发货清单 | OWO1: 贵州航天精工发货清单 | OXE1: 贵州航天精工发货清单 | OXU1: 贵州航天精工发货清单 | OYK1: 贵州航天精工发货清单 | OZA1: 贵州航天精工发货清单 | OZQ1: 贵州航天精工发货清单 | PAG1: 贵州航天精工发货清单 | PAW1: 贵州航天精工发货清单 | PBM1: 贵州航天精工发货清单 | PCC1: 贵州航天精工发货清单 | PCS1: 贵州航天精工发货清单 | PDI1: 贵州航天精工发货清单 | PDY1: 贵州航天精工发货清单 | PEO1: 贵州航天精工发货清单 | PFE1: 贵州航天精工发货清单 | PFU1: 贵州航天精工发货清单 | PGK1: 贵州航天精工发货清单 | PHA1: 贵州航天精工发货清单 | PHQ1: 贵州航天精工发货清单 | PIG1: 贵州航天精工发货清单 | PIW1: 贵州航天精工发货清单 | PJM1: 贵州航天精工发货清单 | PKC1: 贵州航天精工发货清单 | PKS1: 贵州航天精工发货清单 | PLI1: 贵州航天精工发货清单 | PLY1: 贵州航天精工发货清单 | PMO1: 贵州航天精工发货清单 | PNE1: 贵州航天精工发货清单 | PNU1: 贵州航天精工发货清单 | POK1: 贵州航天精工发货清单 | PPA1: 贵州航天精工发货清单 | PPQ1: 贵州航天精工发货清单 | PQG1: 贵州航天精工发货清单 | PQW1: 贵州航天精工发货清单 | PRM1: 贵州航天精工发货清单 | PSC1: 贵州航天精工发货清单 | PSS1: 贵州航天精工发货清单 | PTI1: 贵州航天精工发货清单 | PTY1: 贵州航天精工发货清单 | PUO1: 贵州航天精工发货清单 | PVE1: 贵州航天精工发货清单 | PVU1: 贵州航天精工发货清单 | PWK1: 贵州航天精工发货清单 | PXA1: 贵州航天精工发货清单 | PXQ1: 贵州航天精工发货清单 | PYG1: 贵州航天精工发货清单 | PYW1: 贵州航天精工发货清单 | PZM1: 贵州航天精工发货清单 | QAC1: 贵州航天精工发货清单 | QAS1: 贵州航天精工发货清单 | QBI1: 贵州航天精工发货清单 | QBY1: 贵州航天精工发货清单 | QCO1: 贵州航天精工发货清单 | QDE1: 贵州航天精工发货清单 | QDU1: 贵州航天精工发货清单 | QEK1: 贵州航天精工发货清单 | QFA1: 贵州航天精工发货清单 | QFQ1: 贵州航天精工发货清单 | QGG1: 贵州航天精工发货清单 | QGW1: 贵州航天精工发货清单 | QHM1: 贵州航天精工发货清单 | QIC1: 贵州航天精工发货清单 | QIS1: 贵州航天精工发货清单 | QJI1: 贵州航天精工发货清单 | QJY1: 贵州航天精工发货清单 | QKO1: 贵州航天精工发货清单 | QLE1: 贵州航天精工发货清单 | QLU1: 贵州航天精工发货清单 | QMK1: 贵州航天精工发货清单 | QNA1: 贵州航天精工发货清单 | QNQ1: 贵州航天精工发货清单 | QOG1: 贵州航天精工发货清单 | QOW1: 贵州航天精工发货清单 | QPM1: 贵州航天精工发货清单 | QQC1: 贵州航天精工发货清单 | QQS1: 贵州航天精工发货清单 | QRI1: 贵州航天精工发货清单 | QRY1: 贵州航天精工发货清单 | QSO1: 贵州航天精工发货清单 | QTE1: 贵州航天精工发货清单 | QTU1: 贵州航天精工发货清单 | QUK1: 贵州航天精工发货清单 | QVA1: 贵州航天精工发货清单 | QVQ1: 贵州航天精工发货清单 | QWG1: 贵州航天精工发货清单 | QWW1: 贵州航天精工发货清单 | QXM1: 贵州航天精工发货清单 | QYC1: 贵州航天精工发货清单 | QYS1: 贵州航天精工发货清单 | QZI1: 贵州航天精工发货清单 | QZY1: 贵州航天精工发货清单 | RAO1: 贵州航天精工发货清单 | RBE1: 贵州航天精工发货清单 | RBU1: 贵州航天精工发货清单 | RCK1: 贵州航天精工发货清单 | RDA1: 贵州航天精工发货清单 | RDQ1: 贵州航天精工发货清单 | REG1: 贵州航天精工发货清单 | REW1: 贵州航天精工发货清单 | RFM1: 贵州航天精工发货清单 | RGC1: 贵州航天精工发货清单 | RGS1: 贵州航天精工发货清单 | RHI1: 贵州航天精工发货清单 | RHY1: 贵州航天精工发货清单 | RIO1: 贵州航天精工发货清单 | RJE1: 贵州航天精工发货清单 | RJU1: 贵州航天精工发货清单 | RKK1: 贵州航天精工发货清单 | RLA1: 贵州航天精工发货清单 | RLQ1: 贵州航天精工发货清单 | RMG1: 贵州航天精工发货清单 | RMW1: 贵州航天精工发货清单 | RNM1: 贵州航天精工发货清单 | ROC1: 贵州航天精工发货清单 | ROS1: 贵州航天精工发货清单 | RPI1: 贵州航天精工发货清单 | RPY1: 贵州航天精工发货清单 | RQO1: 贵州航天精工发货清单 | RRE1: 贵州航天精工发货清单 | RRU1: 贵州航天精工发货清单 | RSK1: 贵州航天精工发货清单 | RTA1: 贵州航天精工发货清单 | RTQ1: 贵州航天精工发货清单 | RUG1: 贵州航天精工发货清单 | RUW1: 贵州航天精工发货清单 | RVM1: 贵州航天精工发货清单 | RWC1: 贵州航天精工发货清单 | RWS1: 贵州航天精工发货清单 | RXI1: 贵州航天精工发货清单 | RXY1: 贵州航天精工发货清单 | RYO1: 贵州航天精工发货清单 | RZE1: 贵州航天精工发货清单 | RZU1: 贵州航天精工发货清单 | SAK1: 贵州航天精工发货清单 | SBA1: 贵州航天精工发货清单 | SBQ1: 贵州航天精工发货清单 | SCG1: 贵州航天精工发货清单 | SCW1: 贵州航天精工发货清单 | SDM1: 贵州航天精工发货清单 | SEC1: 贵州航天精工发货清单 | SES1: 贵州航天精工发货清单 | SFI1: 贵州航天精工发货清单 | SFY1: 贵州航天精工发货清单 | SGO1: 贵州航天精工发货清单 | SHE1: 贵州航天精工发货清单 | SHU1: 贵州航天精工发货清单 | SIK1: 贵州航天精工发货清单 | SJA1: 贵州航天精工发货清单 | SJQ1: 贵州航天精工发货清单 | SKG1: 贵州航天精工发货清单 | SKW1: 贵州航天精工发货清单 | SLM1: 贵州航天精工发货清单 | SMC1: 贵州航天精工发货清单 | SMS1: 贵州航天精工发货清单 | SNI1: 贵州航天精工发货清单 | SNY1: 贵州航天精工发货清单 | SOO1: 贵州航天精工发货清单 | SPE1: 贵州航天精工发货清单 | SPU1: 贵州航天精工发货清单 | SQK1: 贵州航天精工发货清单 | SRA1: 贵州航天精工发货清单 | SRQ1: 贵州航天精工发货清单 | SSG1: 贵州航天精工发货清单 | SSW1: 贵州航天精工发货清单 | STM1: 贵州航天精工发货清单 | SUC1: 贵州航天精工发货清单 | SUS1: 贵州航天精工发货清单 | SVI1: 贵州航天精工发货清单 | SVY1: 贵州航天精工发货清单 | SWO1: 贵州航天精工发货清单 | SXE1: 贵州航天精工发货清单 | SXU1: 贵州航天精工发货清单 | SYK1: 贵州航天精工发货清单 | SZA1: 贵州航天精工发货清单 | SZQ1: 贵州航天精工发货清单 | TAG1: 贵州航天精工发货清单 | TAW1: 贵州航天精工发货清单 | TBM1: 贵州航天精工发货清单 | TCC1: 贵州航天精工发货清单 | TCS1: 贵州航天精工发货清单 | TDI1: 贵州航天精工发货清单 | TDY1: 贵州航天精工发货清单 | TEO1: 贵州航天精工发货清单 | TFE1: 贵州航天精工发货清单 | TFU1: 贵州航天精工发货清单 | TGK1: 贵州航天精工发货清单 | THA1: 贵州航天精工发货清单 | THQ1: 贵州航天精工发货清单 | TIG1: 贵州航天精工发货清单 | TIW1: 贵州航天精工发货清单 | TJM1: 贵州航天精工发货清单 | TKC1: 贵州航天精工发货清单 | TKS1: 贵州航天精工发货清单 | TLI1: 贵州航天精工发货清单 | TLY1: 贵州航天精工发货清单 | TMO1: 贵州航天精工发货清单 | TNE1: 贵州航天精工发货清单 | TNU1: 贵州航天精工发货清单 | TOK1: 贵州航天精工发货清单 | TPA1: 贵州航天精工发货清单 | TPQ1: 贵州航天精工发货清单 | TQG1: 贵州航天精工发货清单 | TQW1: 贵州航天精工发货清单 | TRM1: 贵州航天精工发货清单 | TSC1: 贵州航天精工发货清单 | TSS1: 贵州航天精工发货清单 | TTI1: 贵州航天精工发货清单 | TTY1: 贵州航天精工发货清单 | TUO1: 贵州航天精工发货清单 | TVE1: 贵州航天精工发货清单 | TVU1: 贵州航天精工发货清单 | TWK1: 贵州航天精工发货清单 | TXA1: 贵州航天精工发货清单 | TXQ1: 贵州航天精工发货清单 | TYG1: 贵州航天精工发货清单 | TYW1: 贵州航天精工发货清单 | TZM1: 贵州航天精工发货清单 | UAC1: 贵州航天精工发货清单 | UAS1: 贵州航天精工发货清单 | UBI1: 贵州航天精工发货清单 | UBY1: 贵州航天精工发货清单 | UCO1: 贵州航天精工发货清单 | UDE1: 贵州航天精工发货清单 | UDU1: 贵州航天精工发货清单 | UEK1: 贵州航天精工发货清单 | UFA1: 贵州航天精工发货清单 | UFQ1: 贵州航天精工发货清单 | UGG1: 贵州航天精工发货清单 | UGW1: 贵州航天精工发货清单 | UHM1: 贵州航天精工发货清单 | UIC1: 贵州航天精工发货清单 | UIS1: 贵州航天精工发货清单 | UJI1: 贵州航天精工发货清单 | UJY1: 贵州航天精工发货清单 | UKO1: 贵州航天精工发货清单 | ULE1: 贵州航天精工发货清单 | ULU1: 贵州航天精工发货清单 | UMK1: 贵州航天精工发货清单 | UNA1: 贵州航天精工发货清单 | UNQ1: 贵州航天精工发货清单 | UOG1: 贵州航天精工发货清单 | UOW1: 贵州航天精工发货清单 | UPM1: 贵州航天精工发货清单 | UQC1: 贵州航天精工发货清单 | UQS1: 贵州航天精工发货清单 | URI1: 贵州航天精工发货清单 | URY1: 贵州航天精工发货清单 | USO1: 贵州航天精工发货清单 | UTE1: 贵州航天精工发货清单 | UTU1: 贵州航天精工发货清单 | UUK1: 贵州航天精工发货清单 | UVA1: 贵州航天精工发货清单 | UVQ1: 贵州航天精工发货清单 | UWG1: 贵州航天精工发货清单 | UWW1: 贵州航天精工发货清单 | UXM1: 贵州航天精工发货清单 | UYC1: 贵州航天精工发货清单 | UYS1: 贵州航天精工发货清单 | UZI1: 贵州航天精工发货清单 | UZY1: 贵州航天精工发货清单 | VAO1: 贵州航天精工发货清单 | VBE1: 贵州航天精工发货清单 | VBU1: 贵州航天精工发货清单 | VCK1: 贵州航天精工发货清单 | VDA1: 贵州航天精工发货清单 | VDQ1: 贵州航天精工发货清单 | VEG1: 贵州航天精工发货清单 | VEW1: 贵州航天精工发货清单 | VFM1: 贵州航天精工发货清单 | VGC1: 贵州航天精工发货清单 | VGS1: 贵州航天精工发货清单 | VHI1: 贵州航天精工发货清单 | VHY1: 贵州航天精工发货清单 | VIO1: 贵州航天精工发货清单 | VJE1: 贵州航天精工发货清单 | VJU1: 贵州航天精工发货清单 | VKK1: 贵州航天精工发货清单 | VLA1: 贵州航天精工发货清单 | VLQ1: 贵州航天精工发货清单 | VMG1: 贵州航天精工发货清单 | VMW1: 贵州航天精工发货清单 | VNM1: 贵州航天精工发货清单 | VOC1: 贵州航天精工发货清单 | VOS1: 贵州航天精工发货清单 | VPI1: 贵州航天精工发货清单 | VPY1: 贵州航天精工发货清单 | VQO1: 贵州航天精工发货清单 | VRE1: 贵州航天精工发货清单 | VRU1: 贵州航天精工发货清单 | VSK1: 贵州航天精工发货清单 | VTA1: 贵州航天精工发货清单 | VTQ1: 贵州航天精工发货清单 | VUG1: 贵州航天精工发货清单 | VUW1: 贵州航天精工发货清单 | VVM1: 贵州航天精工发货清单 | VWC1: 贵州航天精工发货清单 | VWS1: 贵州航天精工发货清单 | VXI1: 贵州航天精工发货清单 | VXY1: 贵州航天精工发货清单 | VYO1: 贵州航天精工发货清单 | VZE1: 贵州航天精工发货清单 | VZU1: 贵州航天精工发货清单 | WAK1: 贵州航天精工发货清单 | WBA1: 贵州航天精工发货清单 | WBQ1: 贵州航天精工发货清单 | WCG1: 贵州航天精工发货清单 | WCW1: 贵州航天精工发货清单 | WDM1: 贵州航天精工发货清单 | WEC1: 贵州航天精工发货清单 | WES1: 贵州航天精工发货清单 | WFI1: 贵州航天精工发货清单 | WFY1: 贵州航天精工发货清单 | WGO1: 贵州航天精工发货清单 | WHE1: 贵州航天精工发货清单 | WHU1: 贵州航天精工发货清单 | WIK1: 贵州航天精工发货清单 | WJA1: 贵州航天精工发货清单 | WJQ1: 贵州航天精工发货清单 | WKG1: 贵州航天精工发货清单 | WKW1: 贵州航天精工发货清单 | WLM1: 贵州航天精工发货清单 | WMC1: 贵州航天精工发货清单 | WMS1: 贵州航天精工发货清单 | WNI1: 贵州航天精工发货清单 | WNY1: 贵州航天精工发货清单 | WOO1: 贵州航天精工发货清单 | WPE1: 贵州航天精工发货清单 | WPU1: 贵州航天精工发货清单 | WQK1: 贵州航天精工发货清单 | WRA1: 贵州航天精工发货清单 | WRQ1: 贵州航天精工发货清单 | WSG1: 贵州航天精工发货清单 | WSW1: 贵州航天精工发货清单 | WTM1: 贵州航天精工发货清单 | WUC1: 贵州航天精工发货清单 | WUS1: 贵州航天精工发货清单 | WVI1: 贵州航天精工发货清单 | WVY1: 贵州航天精工发货清单 | WWO1: 贵州航天精工发货清单 | WXE1: 贵州航天精工发货清单 | WXU1: 贵州航天精工发货清单 | WYK1: 贵州航天精工发货清单 | WZA1: 贵州航天精工发货清单 | WZQ1: 贵州航天精工发货清单 | XAG1: 贵州航天精工发货清单 | XAW1: 贵州航天精工发货清单 | XBM1: 贵州航天精工发货清单 | XCC1: 贵州航天精工发货清单 | XCS1: 贵州航天精工发货清单 | XDI1: 贵州航天精工发货清单 | XDY1: 贵州航天精工发货清单 | XEO1: 贵州航天精工发货清单
A2: 序号 | B2: 产品名称 | C2: 型号 | D2: 规 格 | E2: 性能等级 | F2: 表面处理 | G2: 材 料 | H2: 订单数量 | I2: 发货数量 | J2: 批次号 | K2: 提货单号 | L2: 箱号 | M2: 发货日期 | N2: 物料号 | O2: 生产日期 | P2: 运单号 | S2: =VLOOKUP(K2,[11]匹配!B:AE,30,FALSE) -> 客户采购订单编号
A3: 1 | D3: 18 | E3: 42-50HRC | F3: Ep·Zn-Ni·c2C | G3: 65Mn | H3: 4100 | I3: 4067 | J3: G02604-069 | K3: 7101108175 | L3: 1-4# | M3: 46139 | N3: 002004000593 | O3: 46137 | R3: 1108175 | S3: G-100015451-260312-0004

Sheet 5702
A1: 贵州航天精工发货清单-5702
A2: 序号 | B2: 产品名称 | C2: 型号 | D2: 规 格 | E2: 性能等级 | F2: 表面处理 | G2: 材 料 | H2: 发货数量 | I2: 批次号 | J2: 提货单号 | K2: 箱号 | L2: 发货日期 | M2: 备注
A3: 1 | D3: - | E3: ≥285HB | G3: GH80A | H3: 60 | I3: G2410-1351 | J3: 7101073263 | K3: 1# | L3: 46080 | M3: 合同号GY-2026-2-0087 | N3: 1073263

Sheet 771
A1: 装 箱 单 | M1: 需跟纸质版清单 并拍照发771发货群 | N1: 董彦楠发货时箱子上贴标签 “空港”
A2: 收货单位：西安微电子技术研究所 | F2: 单据编号：2026.4.27 | K2: 货物总箱数1箱
A3: 提货单号 | B3: 批号 | C3: 采用标准 | D3: 规格 | E3: 材质 | F3: 表面处理 | G3: 性能等级 | H3: 提货数量 | I3: 价格 | J3: 提货金额 | K3: 清单备注邀请 | L3: 箱号
A4: 7101089009 | B4: G2509-1948 | D4: M2×12 | E4: ML1Cr18Ni9Ti | F4: ECP | G4: A2-70 | H4: 76 | I4: 1.5 | J4: 114 | K4: 发771所帅俊岍，同批次发货，提供合格证，尺寸单，试验报告，按照国标或者QJ3112A标准的规定进行性能复验的第三方证明文件并执行双方签订的技术协议，订单号20251230-008，ZGJ, | L4: 1# | M4: 1089009

Sheet 东安实业
A1: 贵州航天精工发货清单-东安实业 | N1: 需拍照发廖庆
A2: 序号 | B2: 产品名称 | C2: 型号 | D2: 规 格 | E2: 性能等级 | F2: 表面处理 | G2: 材 料 | H2: 发货数量 | I2: 批次号 | J2: 提货单号 | K2: 箱号 | L2: 发货日期 | M2: 备注
A3: 1 | D3: M6 | E3: 29-35HRC | F3: Ep·Ag | G3: GH2132 | H3: 85 | I3: G2510-0091 | J3: 7101106011 | K3: 1# | L3: 46135 | M3: 件号：HB5636M6 带试验报告，尺寸报告，材质单，探伤报告，热处理合格证明，表面处理合格证明，产品称重。

Sheet 空空导弹
A1: 贵州航天精工制造有限公司发货清单
A2: 45622
A3: 序号 | B3: 批号 | C3: 产品名称 | D3: 采用标准 | E3: 规格 | F3: 材质 | G3: 表面处理 | H3: 性能等级 | I3: 订单数量 | J3: 提货数量 | K3: 合同号 | L3: 二维码
A4: 1 | B4: G02410-036 | E4: 1.5 | F4: 65Mn | G4: Ct·O | I4: 1890 | J4: 90 | K4: WZ20240804124160 | M4: 7100867648

Sheet 中航飞机起落架
A1: 发货汇总清单-572-2026.4.27产品已发 | J1: =7100&K1 -> 7100
A2: 序号 | B2: 物料名称 | C2: 标准型号 | D2: 规格 | E2: 材料 | F2: 单位 | G2: 数量 | H2: 批次号 | I2: 计划号 | J2: =7100&K2 -> 7100
A3: 1 | D3: 8×12×12 | E3: 20A | F3: 件 | G3: 140 | H3: G2603-2225 | I3: HZB250423 | J3: 7101104767 | K3: 1104767
